pyvoa/__init__.py
pyvoa/__version__.py
pyvoa/error.py
pyvoa/front.py
pyvoa/geo.py
pyvoa/geopd_builder.py
pyvoa/help.py
pyvoa/jsondb_parser.py
pyvoa/kwarg_options.py
pyvoa/tools.py
pyvoa/visu_bokeh.py
pyvoa/visu_folium.py
pyvoa/visu_matplotlib.py
pyvoa/visu_seaborn.py
pyvoa/visualizer.py
pyvoa/data/__init__.py
pyvoa/data/europa.json
pyvoa/data/govcy.json
pyvoa/data/imed.json
pyvoa/data/jhu-usa.json
pyvoa/data/jhu.json
pyvoa/data/logo-pyvoa.png
pyvoa/data/mpoxgh.json
pyvoa/data/owid.json
pyvoa/data/sciensano.json
pyvoa/data/sentinellesIRA.json
pyvoa/data/spf.json
pyvoa/data/spfnational.json
pyvoa/data/sumeau.json
pyvoa-0.4.2.dist-info/LICENSE
pyvoa-0.4.2.dist-info/METADATA
pyvoa-0.4.2.dist-info/WHEEL
pyvoa-0.4.2.dist-info/top_level.txt
pyvoa-0.4.2.dist-info/RECORD
