Metadata-Version: 2.1
Name: pyvoa
Version: 0.4.2
Summary: Python virus open analysis. See more on pyvoa.org
Home-page: https://github.com/pyvoa/pyvoa
Author: pyvoa.org
Author-email: contact@pyvoa.org
License: UNKNOWN
Platform: UNKNOWN
Classifier: Programming Language :: Python :: 3
Classifier: License :: OSI Approved :: MIT License
Classifier: Operating System :: OS Independent
Requires-Python: >=3.8
License-File: LICENSE
Requires-Dist: IPython
Requires-Dist: bs4
Requires-Dist: contextily
Requires-Dist: geopandas
Requires-Dist: lxml
Requires-Dist: numpy
Requires-Dist: pandas
Requires-Dist: pycountry
Requires-Dist: pycountry-convert
Requires-Dist: requests
Requires-Dist: shapely
Requires-Dist: unidecode
